Metadata-Version: 2.1
Name: coconut-ai
Version: 0.2.0
Summary: Coconut AI
Home-page: https://github.com/sae-llm-coconut/coconut-ai
Author: Coconut AI
Requires-Python: >=3.10, <3.11
License-File: LICENSE
Requires-Dist: requests==2.31.0
Requires-Dist: pillow==10.2.0
Requires-Dist: llama-cpp-python==0.2.32
